odoo9_addon_account_fiscal_position_rule-9.0.1.0.0.99.dev30-py3.8-nspkg.pth
odoo_addons/account_fiscal_position_rule/README.rst
odoo_addons/account_fiscal_position_rule/__init__.py
odoo_addons/account_fiscal_position_rule/__openerp__.py
odoo_addons/account_fiscal_position_rule/i18n/account_fiscal_position_rule.pot
odoo_addons/account_fiscal_position_rule/i18n/am.po
odoo_addons/account_fiscal_position_rule/i18n/ar.po
odoo_addons/account_fiscal_position_rule/i18n/bg.po
odoo_addons/account_fiscal_position_rule/i18n/bs.po
odoo_addons/account_fiscal_position_rule/i18n/ca.po
odoo_addons/account_fiscal_position_rule/i18n/ca_ES.po
odoo_addons/account_fiscal_position_rule/i18n/cs.po
odoo_addons/account_fiscal_position_rule/i18n/da.po
odoo_addons/account_fiscal_position_rule/i18n/de.po
odoo_addons/account_fiscal_position_rule/i18n/el_GR.po
odoo_addons/account_fiscal_position_rule/i18n/en_AU.po
odoo_addons/account_fiscal_position_rule/i18n/en_GB.po
odoo_addons/account_fiscal_position_rule/i18n/en_US.po
odoo_addons/account_fiscal_position_rule/i18n/es.po
odoo_addons/account_fiscal_position_rule/i18n/es_AR.po
odoo_addons/account_fiscal_position_rule/i18n/es_CL.po
odoo_addons/account_fiscal_position_rule/i18n/es_CO.po
odoo_addons/account_fiscal_position_rule/i18n/es_CR.po
odoo_addons/account_fiscal_position_rule/i18n/es_DO.po
odoo_addons/account_fiscal_position_rule/i18n/es_EC.po
odoo_addons/account_fiscal_position_rule/i18n/es_ES.po
odoo_addons/account_fiscal_position_rule/i18n/es_MX.po
odoo_addons/account_fiscal_position_rule/i18n/es_PE.po
odoo_addons/account_fiscal_position_rule/i18n/es_PY.po
odoo_addons/account_fiscal_position_rule/i18n/es_VE.po
odoo_addons/account_fiscal_position_rule/i18n/et.po
odoo_addons/account_fiscal_position_rule/i18n/eu.po
odoo_addons/account_fiscal_position_rule/i18n/fa.po
odoo_addons/account_fiscal_position_rule/i18n/fi.po
odoo_addons/account_fiscal_position_rule/i18n/fr.po
odoo_addons/account_fiscal_position_rule/i18n/fr_CA.po
odoo9_addon_account_fiscal_position_rule-9.0.1.0.0.99.dev30.dist-info/METADATA
odoo9_addon_account_fiscal_position_rule-9.0.1.0.0.99.dev30.dist-info/WHEEL
odoo9_addon_account_fiscal_position_rule-9.0.1.0.0.99.dev30.dist-info/namespace_packages.txt
odoo9_addon_account_fiscal_position_rule-9.0.1.0.0.99.dev30.dist-info/top_level.txt
odoo9_addon_account_fiscal_position_rule-9.0.1.0.0.99.dev30.dist-info/RECORD
